#[allow(dead_code)]
#[allow(non_camel_case_types)]
pub enum Opcodes {
    AALOAD = 0x32,
    AASTORE = 0x53,
    ACONSTNULL = 0x01,
    ALOAD = 0x19,
    ALOAD0 = 0x2a,
    ALOAD1 = 0x2b,
    ALOAD2 = 0x2c,
    ALOAD3 = 0x2d,
    ANEWARRAY = 0xbd,
    ARETURN = 0xb0,
    ARRAYLENGTH = 0xbe,
    ASTORE = 0x3a,
    ASTORE0 = 0x4b,
    ASTORE1 = 0x4c,
    ASTORE2 = 0x4d,
    ASTORE3 = 0x4e,
    ATHROW = 0xbf,
    BALOAD = 0x33,
    BASTORE = 0x54,
    BIPUSH = 0x10,
    BREAKPOINT = 0xca,
    CALOAD = 0x34,
    CASTORE = 0x55,
    CHECKCAST = 0xc0,
    D2F = 0x90,
    D2I = 0x8e,
    D2L = 0x8f,
    DADD = 0x63,
    DALOD = 0x31,
    DASTORE = 0x52,
    DCMPG = 0x98,
    DCMPL = 0x97,
    DCONST0 = 0x0e,
    DCONST1 = 0x0f,
    DDIV = 0x6f,
    DLOAD = 0x18,
    DLOAD0 = 0x26,
    DLOAD1 = 0x27,
    DLOAD2 = 0x28,
    DLOAD3 = 0x29,
    DMUL = 0x6b,
    DNEG = 0x77,
    DREM = 0x73,
    DRETURN = 0xaf,
    DSTORE = 0x39,
    DSTORE0 = 0x47,
    DSTORE1 = 0x48,
    DSTORE2 = 0x49,
    DSTORE3 = 0x4a,
    DSUB = 0x67,
    DUP = 0x59,
    DUPX1 = 0x5a,
    DUPX2 = 0x5b,
    DUP2 = 0x5c,
    DUP2X1 = 0x5d,
    DUP2X2 = 0x5e,
    F2D = 0x8d,
    F2I = 0x8b,
    F2L = 0x8c,
    FADD = 0x62,
    FALOAD = 0x30,
    FASTORE = 0x51,
    FCMPG = 0x96,
    FCMPL = 0x95,
    FCONST0 = 0x0b,
    FCONST1 = 0x0c,
    FCONST2 = 0x0d,
    FDIV = 0x6e,
    FLOAD = 0x17,
    FLOAD0 = 0x22,
    FLOAD1 = 0x23,
    FLOAD2 = 0x24,
    FLOAD3 = 0x25,
    FMUL = 0x6a,
    FNEG = 0x76,
    FREM = 0x72,
    FRETURN = 0xae,
    FSTORE = 0x38,
    FSTORE0 = 0x43,
    FSTORE1 = 0x44,
    FSTORE2 = 0x45,
    FSTORE3 = 0x46,
    FSUB = 0x66,
    GETFIELD = 0xb4,
    GETSTATIC = 0xb2,
    GOTO = 0xa7,
    GOTOW = 0xc8,
    I2B = 0x91,
    I2C = 0x92,
    I2D = 0x87,
    I2F = 0x86,
    I2L = 0x85,
    I2S = 0x93,
    IADD = 0x60,
    IALOAD = 0x2e,
    IAND = 0x7e,
    IASTORE = 0x4f,
    ICONSTM1 = 0x02,
    ICONST0 = 0x03,
    ICONST1 = 0x04,
    ICONST2 = 0x05,
    ICONST3 = 0x06,
    ICONST4 = 0x07,
    ICONST5 = 0x08,
    IDIV = 0x6c,
    IF_ACMPEQ = 0xa5,
    IF_ACMPNE = 0xA6,
    IF_ICMPEQ = 0x9f,
    IF_ICMPGE = 0xa2,
    IF_ICMPGT = 0xa3,
    IF_ICMPLE = 0xa4,
    IF_ICMPLT = 0xa1,
    IF_ICMPNE = 0xa0,
    IFEQ = 0x99,
    IFGE = 0x9c,
    IFGT = 0x9d,
    IFLE = 0x9e,
    IFLT = 0x9b,
    IFNE = 0x9a,
    IFNONNULL = 0xc7,
    IFNULL = 0xc6,
    IINC = 0x84,
    ILOAD = 0x15,
    ILOAD0 = 0x1a,
    ILOAD1 = 0x1b,
    ILOAD2 = 0x1c,
    ILOAD3 = 0x1d,
    IMPDEP1 = 0xfe,
    IMPDEP2 = 0xff,
    IMUL = 0x68,
    INEG = 0x74,
    INSTANCEOF = 0xc1,
    INVOKEDYNAMIC = 0xba,
    INVOKEINTERFACE = 0xb9,
    INVOKESPECIAL = 0xb7,
    INVOKESTATIC = 0xb8,
    INVOKEVIRTUAL = 0xb6,
    IOR = 0x80,
    IREM = 0x70,
    IRETURN = 0xac,
    ISHL = 0x78,
    ISHR = 0x7a,
    ISTORE = 0x36,
    ISTORE0 = 0x3b,
    ISTORE1 = 0x3c,
    ISTORE2 = 0x3d,
    ISTORE3 = 0x3e,
    ISUB = 0x64,
    IUSHR = 0x7c,
    IXOR = 0x82,
    JSR = 0xa8,
    JSR_W = 0xc9,
    L2D = 0x8a,
    L2F = 0x89,
    L2I = 0x88,
    LADD = 0x61,
    LALOAD = 0x2f,
    LAND = 0x7f,
    LASTORE = 0x50,
    LCMP = 0x94,
    LCONST_0 = 0x09,
    LCONST_1 = 0x0a,
    LDC = 0x12,
    LDC_W = 0x13,
    LDC2_W = 0x14,
    LDIV = 0x6d,
    LLOAD = 0x16,
    LLOAD_0 = 0x1e,
    LLOAD_1 = 0x1f,
    LLOAD_2 = 0x20,
    LLOAD_3 = 0x21,
    LMUL = 0x69,
    LNEG = 0x75,
    LOOKUPSWITCH = 0xab,
    LOR = 0x81,
    LREM = 0x71,
    LRETURN = 0xad,
    LSHL = 0x79,
    LSHR = 0x7b,
    LSTORE = 0x37,
    LSTORE_0 = 0x3f,
    LSTORE_1 = 0x40,
    LSTORE_2 = 0x41,
    LSTORE_3 = 0x42,
    LSUB = 0x65,
    LUSHR = 0x7d,
    LXOR = 0x83,
    MONITORENTER = 0xc2,
    MONITOREXIT = 0xc3,
    MULTIANEWARRAY = 0xc5,
    NEW = 0xbb,
    NEWARRAY = 0xbc,
    NOP = 0x00,
    POP = 0x57,
    POP2 = 0x58,
    PUTFIELD = 0xb5,
    PUTSTATIC = 0xb3,
    RET = 0xa9,
    RETURN = 0xb1,
    SALOAD = 0x35,
    SASTORE = 0x56,
    SIPUSH = 0x11,
    SWAP = 0x5f,
    TABLESWITCH = 0xaa,
    WIDE = 0xc4,
}
